ansys/units/__init__.py
ansys/units/_constants.py
ansys/units/_version.py
ansys/units/base_dimensions.py
ansys/units/cfg.yaml
ansys/units/common.py
ansys/units/dimensions.py
ansys/units/quantity.py
ansys/units/quantity_dimensions.py
ansys/units/systems.py
ansys/units/unit.py
ansys/units/unit_registry.py
ansys/units/docs/.gitignore
ansys/units/quantity_tables/bt_table.yaml
ansys/units/quantity_tables/cgs_table.yaml
ansys/units/quantity_tables/keys.py
ansys/units/quantity_tables/si_table.yaml
ansys/units/variable_descriptor/__init__.py
ansys/units/variable_descriptor/strategy.py
ansys/units/variable_descriptor/variable_descriptor.py
ansys_units-0.9.1.dist-info/licenses/LICENSE
ansys_units-0.9.1.dist-info/WHEEL
ansys_units-0.9.1.dist-info/METADATA
ansys_units-0.9.1.dist-info/RECORD
