Metadata-Version: 2.4
Name: ansys-units
Version: 0.9.1
Summary: Pythonic interface for units, unit systems, and unit conversions.
Author-email: "ANSYS, Inc." <pyansys.core@ansys.com>
Maintainer-email: "ANSYS, Inc." <pyansys.core@ansys.com>
Requires-Python: >=3.10,<3.14
Classifier: Development Status :: 4 - Beta
Classifier: Intended Audience :: Science/Research
Classifier: Topic :: Scientific/Engineering :: Information Analysis
Classifier: License :: OSI Approved :: MIT License
Classifier: Operating System :: OS Independent
Classifier: Programming Language :: Python :: 3
License-File: LICENSE
Requires-Dist: importlib-metadata>=4.0
Requires-Dist: pyyaml>=6.0
Requires-Dist: numpy>=1.24,<3 ; extra == "additional"
Requires-Dist: pydantic>=2.11.7 ; extra == "additional"
Requires-Dist: pydantic_core>=2.33.2 ; extra == "additional"
Requires-Dist: matplotlib==3.10.7 ; extra == "ci-types"
Requires-Dist: pydantic>=2.11.7 ; extra == "ci-types"
Requires-Dist: pydantic_core>=2.33.2 ; extra == "ci-types"
Requires-Dist: pytest==8.4.2 ; extra == "ci-types"
Requires-Dist: pytest-cov==7.0.0 ; extra == "ci-types"
Requires-Dist: pytest-mock==3.15.1 ; extra == "ci-types"
Requires-Dist: pint==0.24.4 ; extra == "ci-types"
Requires-Dist: black==24.10.0 ; extra == "ci-types"
Requires-Dist: ansys-sphinx-theme==1.6.3 ; extra == "doc"
Requires-Dist: pdf2image==1.17.0 ; extra == "doc"
Requires-Dist: quarto-cli==1.8.25 ; extra == "doc"
Requires-Dist: matplotlib==3.10.7 ; extra == "doc"
Requires-Dist: numpydoc==1.9.0 ; extra == "doc"
Requires-Dist: Sphinx==7.4.7 ; extra == "doc"
Requires-Dist: sphinx-copybutton==0.5.2 ; extra == "doc"
Requires-Dist: sphinx-gallery==0.19.0 ; extra == "doc"
Requires-Dist: sphinx-toggleprompt==0.6.0 ; extra == "doc"
Requires-Dist: numpy>=1.24,<3 ; extra == "tests"
Requires-Dist: pytest==8.4.2 ; extra == "tests"
Requires-Dist: pytest-cov==7.0.0 ; extra == "tests"
Requires-Dist: pytest-mock==3.15.1 ; extra == "tests"
Requires-Dist: pint==0.24.4 ; extra == "tests"
Project-URL: Documentation, https://units.docs.pyansys.com/
Project-URL: Issues, https://github.com/ansys/pyansys-units/issues
Project-URL: Releases, https://github.com/ansys/pyansys-units/releases
Project-URL: Source, https://github.com/ansys/pyansys-units
Provides-Extra: additional
Provides-Extra: ci-types
Provides-Extra: doc
Provides-Extra: tests
